maintenance_panel/__init__.py
maintenance_panel/admin.py
maintenance_panel/apps.py
maintenance_panel/context_processors.py
maintenance_panel/middleware.py
maintenance_panel/models.py
maintenance_panel/migrations/__init__.py
maintenance_panel/templates/maintenance_panel/maintenance.html
django_maintenance_panel-0.1.0.dist-info/METADATA
django_maintenance_panel-0.1.0.dist-info/WHEEL
django_maintenance_panel-0.1.0.dist-info/top_level.txt
django_maintenance_panel-0.1.0.dist-info/RECORD
