Metadata-Version: 2.4
Name: django-maintenance-panel
Version: 0.1.0
Summary: Django maintenance panel: show maintenance page only to staff (non-superuser) while allowing superusers and public users.
Author-email: Your Name <you@example.com>
License: MIT
Keywords: django,maintenance,admin,panel
Classifier: Framework :: Django
Classifier: Framework :: Django :: 4
Classifier: Programming Language :: Python :: 3
Classifier: License :: OSI Approved :: MIT License
Classifier: Development Status :: 3 - Alpha
Classifier: Environment :: Web Environment
Requires-Python: >=3.9
Requires-Dist: Django>=4.2
